mini_ml/MiniML.py
mini_ml/__init__.py
MiniML-0.0.1.dist-info/AUTHORS
MiniML-0.0.1.dist-info/METADATA
MiniML-0.0.1.dist-info/WHEEL
MiniML-0.0.1.dist-info/top_level.txt
MiniML-0.0.1.dist-info/RECORD
